{"nodes":[{"id":"applications_utils","label":"utils.ts","file_type":"code","source_file":"/Users/duarteelton/Desktop/OFM PROJECT/halo-talent/app/(admin)/admin/applications/utils.ts","source_location":"L1"},{"id":"applications_utils_units","label":"units","file_type":"code","source_file":"/Users/duarteelton/Desktop/OFM PROJECT/halo-talent/app/(admin)/admin/applications/utils.ts","source_location":"L1"},{"id":"applications_utils_relativetime","label":"relativeTime()","file_type":"code","source_file":"/Users/duarteelton/Desktop/OFM PROJECT/halo-talent/app/(admin)/admin/applications/utils.ts","source_location":"L11"},{"id":"applications_utils_formatdate","label":"formatDate()","file_type":"code","source_file":"/Users/duarteelton/Desktop/OFM PROJECT/halo-talent/app/(admin)/admin/applications/utils.ts","source_location":"L24"},{"id":"applications_utils_formatshortdate","label":"formatShortDate()","file_type":"code","source_file":"/Users/duarteelton/Desktop/OFM PROJECT/halo-talent/app/(admin)/admin/applications/utils.ts","source_location":"L34"}],"edges":[{"source":"applications_utils","target":"applications_utils_units","relation":"contains","confidence":"EXTRACTED","source_file":"/Users/duarteelton/Desktop/OFM PROJECT/halo-talent/app/(admin)/admin/applications/utils.ts","source_location":"L1","weight":1},{"source":"applications_utils","target":"applications_utils_relativetime","relation":"contains","confidence":"EXTRACTED","source_file":"/Users/duarteelton/Desktop/OFM PROJECT/halo-talent/app/(admin)/admin/applications/utils.ts","source_location":"L11","weight":1},{"source":"applications_utils","target":"applications_utils_formatdate","relation":"contains","confidence":"EXTRACTED","source_file":"/Users/duarteelton/Desktop/OFM PROJECT/halo-talent/app/(admin)/admin/applications/utils.ts","source_location":"L24","weight":1},{"source":"applications_utils","target":"applications_utils_formatshortdate","relation":"contains","confidence":"EXTRACTED","source_file":"/Users/duarteelton/Desktop/OFM PROJECT/halo-talent/app/(admin)/admin/applications/utils.ts","source_location":"L34","weight":1}]}