{"nodes":[{"id":"atlas_atlasshared","label":"AtlasShared.tsx","file_type":"code","source_file":"/Users/duarteelton/Desktop/OFM PROJECT/halo-talent/components/atlas/AtlasShared.tsx","source_location":"L1"},{"id":"atlas_atlasshared_atlasskeleton","label":"AtlasSkeleton()","file_type":"code","source_file":"/Users/duarteelton/Desktop/OFM PROJECT/halo-talent/components/atlas/AtlasShared.tsx","source_location":"L7"},{"id":"atlas_atlasshared_atlaspageskeleton","label":"AtlasPageSkeleton()","file_type":"code","source_file":"/Users/duarteelton/Desktop/OFM PROJECT/halo-talent/components/atlas/AtlasShared.tsx","source_location":"L29"},{"id":"atlas_atlasshared_cardskeleton","label":"CardSkeleton()","file_type":"code","source_file":"/Users/duarteelton/Desktop/OFM PROJECT/halo-talent/components/atlas/AtlasShared.tsx","source_location":"L68"},{"id":"atlas_atlasshared_empty_illustrations","label":"EMPTY_ILLUSTRATIONS","file_type":"code","source_file":"/Users/duarteelton/Desktop/OFM PROJECT/halo-talent/components/atlas/AtlasShared.tsx","source_location":"L79"},{"id":"atlas_atlasshared_atlasemptystate","label":"AtlasEmptyState()","file_type":"code","source_file":"/Users/duarteelton/Desktop/OFM PROJECT/halo-talent/components/atlas/AtlasShared.tsx","source_location":"L88"}],"edges":[{"source":"atlas_atlasshared","target":"lucide_react","relation":"imports_from","confidence":"EXTRACTED","source_file":"/Users/duarteelton/Desktop/OFM PROJECT/halo-talent/components/atlas/AtlasShared.tsx","source_location":"L3","weight":1},{"source":"atlas_atlasshared","target":"atlas_atlasshared_atlasskeleton","relation":"contains","confidence":"EXTRACTED","source_file":"/Users/duarteelton/Desktop/OFM PROJECT/halo-talent/components/atlas/AtlasShared.tsx","source_location":"L7","weight":1},{"source":"atlas_atlasshared","target":"atlas_atlasshared_atlaspageskeleton","relation":"contains","confidence":"EXTRACTED","source_file":"/Users/duarteelton/Desktop/OFM PROJECT/halo-talent/components/atlas/AtlasShared.tsx","source_location":"L29","weight":1},{"source":"atlas_atlasshared","target":"atlas_atlasshared_cardskeleton","relation":"contains","confidence":"EXTRACTED","source_file":"/Users/duarteelton/Desktop/OFM PROJECT/halo-talent/components/atlas/AtlasShared.tsx","source_location":"L68","weight":1},{"source":"atlas_atlasshared","target":"atlas_atlasshared_empty_illustrations","relation":"contains","confidence":"EXTRACTED","source_file":"/Users/duarteelton/Desktop/OFM PROJECT/halo-talent/components/atlas/AtlasShared.tsx","source_location":"L79","weight":1},{"source":"atlas_atlasshared","target":"atlas_atlasshared_atlasemptystate","relation":"contains","confidence":"EXTRACTED","source_file":"/Users/duarteelton/Desktop/OFM PROJECT/halo-talent/components/atlas/AtlasShared.tsx","source_location":"L88","weight":1}]}